pyIPCMI.Parser.Rules-1.1.5-py3.6-nspkg.pth
pyIPCMI/Parser/Rules/CodeDOM.py
pyIPCMI/Parser/Rules/__init__.py
pyIPCMI.Parser.Rules-1.1.5.dist-info/LICENSE.md
pyIPCMI.Parser.Rules-1.1.5.dist-info/METADATA
pyIPCMI.Parser.Rules-1.1.5.dist-info/WHEEL
pyIPCMI.Parser.Rules-1.1.5.dist-info/namespace_packages.txt
pyIPCMI.Parser.Rules-1.1.5.dist-info/top_level.txt
pyIPCMI.Parser.Rules-1.1.5.dist-info/RECORD
