Metadata-Version: 2.1
Name: pyIPCMI.Parser.Rules
Version: 1.1.5
Summary: A parser for `*.rules` files used in pyIPCMI.
Home-page: https://github.com/Paebbels/pyIPCMI.Parser.Rules
Author: Patrick Lehmann
Author-email: Paebbels@gmail.com
License: UNKNOWN
Project-URL: Documentation, https://pyIPCMI.Parser.Rules.readthedocs.io/en/latest/
Project-URL: Source Code, https://github.com/Paebbels/pyIPCMI.Parser.Rules
Project-URL: Issue Tracker, https://github.com/Paebbels/pyIPCMI.Parser.Rules/issues
Keywords: Python3 Parser pyIPCMI Code-DOM
Platform: UNKNOWN
Classifier: License :: OSI Approved :: Apache Software License
Classifier: Operating System :: OS Independent
Classifier: Programming Language :: Python :: 3 :: Only
Classifier: Programming Language :: Python :: 3.5
Classifier: Programming Language :: Python :: 3.6
Classifier: Programming Language :: Python :: 3.7
Classifier: Programming Language :: Python :: 3.8
Classifier: Development Status :: 5 - Production/Stable
Classifier: Intended Audience :: Developers
Classifier: Topic :: Utilities
Requires-Python: >=3.5
Requires-Dist: pyTokenizer
Requires-Dist: pyExploringCodeDOMParser
